gsem/__init__.py
gsem/cli.py
gsem/config.py
gsem/extension.py
gsem/utils.py
gsem-0.2.3.dist-info/LICENSE
gsem-0.2.3.dist-info/METADATA
gsem-0.2.3.dist-info/WHEEL
gsem-0.2.3.dist-info/entry_points.txt
gsem-0.2.3.dist-info/RECORD
