Metadata-Version: 2.1
Name: gsem
Version: 0.2.3
Summary: Command line extension manager for Gnome-Shell
Home-page: https://github.com/andriykohut/gsem
License: MIT
Keywords: gnome-shell,gnome,cli,command-line-tool,gnome-shell-extension
Author: Andrii Kohut
Author-email: kogut.andriy@gmail.com
Requires-Python: >=3.7
Classifier: License :: OSI Approved :: MIT License
Classifier: Programming Language :: Python :: 3
Classifier: Programming Language :: Python :: 3.7
Classifier: Programming Language :: Python :: 3.8
Classifier: Programming Language :: Python :: 3.9
Classifier: Programming Language :: Python :: 3.10
Classifier: Programming Language :: Python :: 3.11
Classifier: Topic :: Desktop Environment :: Gnome
Requires-Dist: PyGObject (>=3.0)
Project-URL: Repository, https://github.com/andriykohut/gsem
